Configs/__init__.py
Core/Column.py
Core/Enum_Type.py
Core/Interface.py
Core/Table.py
Core/__init__.py
Core/Granularity/Granularity.py
Core/Granularity/GranularityTemporal.py
Core/Granularity/GranularityTimeInterval.py
Core/Granularity/__init__.py
Metrics/Metric.py
Metrics/MetricColumn.py
Metrics/MetricContext.py
Metrics/MetricFile.py
Metrics/MetricService.py
Metrics/__init__.py
Metrics/MetricExpressions/MetricExpression.py
Metrics/MetricExpressions/MetricExpressionNullValue.py
Metrics/MetricExpressions/__init__.py
Metrics/MetricResult/MetricResult.py
Metrics/MetricResult/MetricResultAgg.py
Metrics/MetricResult/MetricResultValidation.py
Metrics/MetricResult/__init__.py
Source/Source.py
Source/__init__.py
Source/SourceBBDD/SourceHIVE.py
Source/SourceBBDD/__init__.py
Source/SourceFile/SourceCSV.py
Source/SourceFile/SourceFile.py
Source/SourceFile/__init__.py
Test/Test.py
Test/TestResult.py
Test/TestService.py
Test/__init__.py
Test/TestOperations/TestOperation.py
Test/TestOperations/TestOperationMayor.py
Test/TestOperations/TestOperationMinor.py
Test/TestOperations/__init__.py
Test/TestRepresentations/TestRepresentation.py
Test/TestRepresentations/TestRepresentationPercentage.py
Test/TestRepresentations/TestRepresentationValue.py
Test/TestRepresentations/__init__.py
lucumaproject-1.1.6.dist-info/DESCRIPTION.rst
lucumaproject-1.1.6.dist-info/METADATA
lucumaproject-1.1.6.dist-info/RECORD
lucumaproject-1.1.6.dist-info/WHEEL
lucumaproject-1.1.6.dist-info/metadata.json
lucumaproject-1.1.6.dist-info/top_level.txt
