Metadata-Version: 2.0
Name: lucumaproject
Version: 1.1.6
Summary: A sample Python project
Home-page: https://github.com/pypa/lucumaproject
Author: The Python Packaging Authority
Author-email: pypa-dev@googlegroups.com
License: UNKNOWN
Keywords: sample setuptools development
Platform: UNKNOWN
Classifier: Development Status :: 3 - Alpha
Classifier: Intended Audience :: Developers
Classifier: Topic :: Software Development :: Build Tools
Classifier: License :: OSI Approved :: MIT License
Classifier: Programming Language :: Python :: 2
Classifier: Programming Language :: Python :: 2.7
Classifier: Programming Language :: Python :: 3
Classifier: Programming Language :: Python :: 3.4
Classifier: Programming Language :: Python :: 3.5
Classifier: Programming Language :: Python :: 3.6
Requires-Dist: enum34
